keepr/__init__.py
keepr/cli.py
keepr/db.py
keepr/internal_config.py
keepr/password_generator.py
keepr/security.py
keepr/session.py
keepr/sql_queries.py
keepr/user_config.py
keepr-1.1.0.dist-info/licenses/LICENSE.md
keepr-1.1.0.dist-info/WHEEL
keepr-1.1.0.dist-info/entry_points.txt
keepr-1.1.0.dist-info/METADATA
keepr-1.1.0.dist-info/RECORD
