Metadata-Version: 2.4
Name: Keepr
Version: 1.1.0
Summary: Secure Command-Line Password Manager
Author: Ben Samarji
Author-email: Ben Samarji <bensamarji5637@gmail.com>
License-Expression: MIT
License-File: LICENSE.md
Classifier: Programming Language :: Python :: 3
Classifier: Operating System :: OS Independent
Requires-Dist: click==8.3.0
Requires-Dist: tabulate==0.9.0
Requires-Dist: pyperclip==1.11.0
Requires-Dist: sqlcipher3-wheels==0.5.5.post0
Requires-Dist: cryptography>=46.0.3
Requires-Dist: pyinstaller>=6.16.0
Requires-Python: >=3.13
Project-URL: Homepage, https://github.com/bsamarji/Keepr
Project-URL: Issues, https://github.com/bsamarji/Keepr/issues
